odoo/addons/web_create_write_confirm/README.rst
odoo/addons/web_create_write_confirm/__init__.py
odoo/addons/web_create_write_confirm/__manifest__.py
odoo/addons/web_create_write_confirm/i18n/web_create_write_confirm.pot
odoo/addons/web_create_write_confirm/models/__init__.py
odoo/addons/web_create_write_confirm/models/base.py
odoo/addons/web_create_write_confirm/models/popup_message.py
odoo/addons/web_create_write_confirm/readme/CONTRIBUTORS.rst
odoo/addons/web_create_write_confirm/readme/DESCRIPTION.rst
odoo/addons/web_create_write_confirm/readme/USAGE.rst
odoo/addons/web_create_write_confirm/security/ir.model.access.csv
odoo/addons/web_create_write_confirm/static/description/icon.png
odoo/addons/web_create_write_confirm/static/description/index.html
odoo/addons/web_create_write_confirm/static/src/js/pop_up_confirmation.js
odoo/addons/web_create_write_confirm/tests/__init__.py
odoo/addons/web_create_write_confirm/tests/test_base_model.py
odoo/addons/web_create_write_confirm/views/assets.xml
odoo/addons/web_create_write_confirm/views/popup_message.xml
odoo14_addon_web_create_write_confirm-14.0.1.2.0.dist-info/METADATA
odoo14_addon_web_create_write_confirm-14.0.1.2.0.dist-info/WHEEL
odoo14_addon_web_create_write_confirm-14.0.1.2.0.dist-info/top_level.txt
odoo14_addon_web_create_write_confirm-14.0.1.2.0.dist-info/RECORD
